[
    {
        "keys":"[\"reward_tp\"]",
        "type":"rewardAd",
        "id":"reward_ad",
        "isAutoLoad":"true"
    },
    {
        "keys":"[\"navive_tp\"]",
        "type":"nativeAd",
        "id":"native_ad",
        "isAutoLoad":"true"
    },
    {
        "keys":"[\"inter_tp\"]",
        "type":"interstitialAd",
        "id":"inter_ad",
        "isAutoLoad":"true"
    },
    {
        "keys":"[\"banner_tp\"]",
        "type":"bannerAd",
        "id":"banner_group",
        "isAutoLoad":"true"
    }
]
